asset_scanner/LICENSE
asset_scanner/__init__.py
asset_scanner/core/__init__.py
asset_scanner/core/decorators.py
asset_scanner/core/exceptions.py
asset_scanner/core/extractor.py
asset_scanner/core/handler_picker.py
asset_scanner/core/item_describer.py
asset_scanner/core/processor.py
asset_scanner/core/utils.py
asset_scanner/plugins/__init__.py
asset_scanner/plugins/extraction_methods/__init__.py
asset_scanner/plugins/extraction_methods/iso19115_extract.py
asset_scanner/plugins/extraction_methods/mixins.py
asset_scanner/plugins/extraction_methods/postprocessors.py
asset_scanner/plugins/extraction_methods/preprocessors.py
asset_scanner/plugins/extraction_methods/regex_extract.py
asset_scanner/plugins/extraction_methods/utils.py
asset_scanner/plugins/extraction_methods/xml_extract.py
asset_scanner/plugins/extraction_methods/header_extract/__init__.py
asset_scanner/plugins/extraction_methods/header_extract/header_extract.py
asset_scanner/plugins/extraction_methods/header_extract/backends/__init__.py
asset_scanner/plugins/extraction_methods/header_extract/backends/cf.py
asset_scanner/plugins/extraction_methods/header_extract/backends/xarray.py
asset_scanner/plugins/filters/__init__.py
asset_scanner/plugins/filters/path_regex.py
asset_scanner/plugins/input_plugins/__init__.py
asset_scanner/plugins/input_plugins/base.py
asset_scanner/plugins/input_plugins/file_system_input.py
asset_scanner/plugins/input_plugins/intake_esm_input.py
asset_scanner/plugins/input_plugins/object_store_input.py
asset_scanner/plugins/input_plugins/rabbit_mq_input.py
asset_scanner/plugins/input_plugins/thredds_input.py
asset_scanner/plugins/output_plugins/__init__.py
asset_scanner/plugins/output_plugins/base.py
asset_scanner/plugins/output_plugins/elasticsearch_backend.py
asset_scanner/plugins/output_plugins/standard_out.py
asset_scanner/scripts/__init__.py
asset_scanner/scripts/asset_scanner.py
asset_scanner/types/__init__.py
asset_scanner/types/source_media.py
asset_scanner-1.0.2.dist-info/METADATA
asset_scanner-1.0.2.dist-info/WHEEL
asset_scanner-1.0.2.dist-info/entry_points.txt
asset_scanner-1.0.2.dist-info/top_level.txt
asset_scanner-1.0.2.dist-info/RECORD
