Metadata-Version: 2.1
Name: asset-scanner
Version: 1.0.2
Summary: Framework to provide plugin architecture to allow the scanning of assets to extract metadata and facets.
Home-page: https://github.com/cedadev/asset-scanner/
Author: Richard Smith
License: BSD - See asset_extractor/LICENSE file for details
Platform: UNKNOWN
Requires-Python: >=3.5
Requires-Dist: pyyaml
Requires-Dist: ceda-directory-tree
Requires-Dist: tqdm
Requires-Dist: pydantic
Provides-Extra: docs
Requires-Dist: sphinx ; extra == 'docs'
Requires-Dist: sphinx-rtd-theme ; extra == 'docs'
Requires-Dist: elasticsearch ; extra == 'docs'
Requires-Dist: sphinxcontrib-programoutput ; extra == 'docs'
Provides-Extra: elasticsearch
Requires-Dist: elasticsearch ; extra == 'elasticsearch'
Provides-Extra: intake-esm
Requires-Dist: intake-esm ; extra == 'intake-esm'
Provides-Extra: rabbitmq
Requires-Dist: pika ; extra == 'rabbitmq'
Provides-Extra: thredds
Requires-Dist: siphon ; extra == 'thredds'
